setup.py
pytailf.egg-info/PKG-INFO
pytailf.egg-info/SOURCES.txt
pytailf.egg-info/dependency_links.txt
pytailf.egg-info/top_level.txt
tailf/__init__.py