Metadata-Version: 1.0
Name: pytailf
Version: 1.0
Summary: Simple python tail -f wrapper
Home-page: https://bitbucket.org/angry_elf/pytailf/
Author: Alexey Loshkarev
Author-email: elf2001@gmail.com
License: GPL
Platform: UNKNOWN
Classifier: Development Status :: 4 - Beta
Classifier: Intended Audience :: Developers
Classifier: License :: OSI Approved :: GNU General Public License (GPL)
Classifier: Natural Language :: English
Classifier: Programming Language :: Python
Classifier: Topic :: Software Development :: Libraries :: Python Modules
